tg_prepare-2.2.6.dist-info/licenses/LICENSE
tg_prepare-2.2.6.dist-info/projects/.secret_key
tgp_backend/__init__.py
tgp_backend/auth.py
tgp_backend/cli.py
tgp_backend/config.py
tgp_backend/directories.py
tgp_backend/interfaces.py
tgp_backend/nextcloud.py
tgp_backend/project.py
tgp_backend/session_manager.py
tgp_backend/tgclient.py
tgp_backend/util.py
tgp_ui/__init__.py
tgp_ui/app.py
tgp_ui/routes/__init__.py
tgp_ui/routes/collection.py
tgp_ui/routes/data.py
tgp_ui/routes/project.py
tgp_ui/routes/publication.py
tgp_ui/routes/tabs.py
tgp_ui/routes/views.py
tgp_ui/static/css/bootstrap-icons.min.css
tgp_ui/static/css/bootstrap.min.css
tgp_ui/static/css/bootstrap.min.css.map
tgp_ui/static/css/main.css
tgp_ui/static/css/navbar.css
tgp_ui/static/css/simpleXML.css
tgp_ui/static/img/favicon.ico
tgp_ui/static/img/textgrid-logo.svg
tgp_ui/static/js/bootstrap.bundle.min.js
tgp_ui/static/js/collectionManager.js
tgp_ui/static/js/fileManager.js
tgp_ui/static/js/jquery.min.js
tgp_ui/static/js/main.js
tgp_ui/static/js/modalManager.js
tgp_ui/static/js/navbarManager.js
tgp_ui/static/js/projectManager.js
tgp_ui/static/js/require.js
tgp_ui/static/js/sidebarManager.js
tgp_ui/static/js/simpleXML.js
tgp_ui/static/js/tabManager.js
tgp_ui/templates/file_tree.html
tgp_ui/templates/layout.html
tgp_ui/templates/macros.html
tgp_ui/templates/nxc_login.html
tgp_ui/templates/nxc_tab.html
tgp_ui/templates/project_main.html
tgp_ui/templates/project_navbar.html
tgp_ui/templates/projects_main.html
tgp_ui/templates/details/empty_container.html
tgp_ui/templates/details/manage_collection.html
tgp_ui/templates/includes/get_sessionid.html
tgp_ui/templates/includes/publish_form.html
tgp_ui/templates/includes/set_sessionid.html
tgp_ui/templates/includes/upload_form.html
tgp_ui/templates/modal/delete_project.html
tgp_ui/templates/modal/empty_container.html
tgp_ui/templates/modal/file_explorer_content.html
tgp_ui/templates/modal/file_explorer_main.html
tgp_ui/templates/modal/file_explorer_nextcloud.html
tgp_ui/templates/modal/github_modal.html
tgp_ui/templates/modal/nextcloud_login.html
tg_prepare-2.2.6.dist-info/METADATA
tg_prepare-2.2.6.dist-info/WHEEL
tg_prepare-2.2.6.dist-info/entry_points.txt
tg_prepare-2.2.6.dist-info/top_level.txt
tg_prepare-2.2.6.dist-info/RECORD
