Metadata-Version: 2.4
Name: tg_prepare
Version: 2.2.6
Summary: Simple UI to handle TextGrid imports visually.
Author: Ralf Klammer, Moritz Wilhelm
Author-email: ralf.klammer@tu-dresden.de, moritz.wilhelm@tu-dresden.de
License-File: LICENSE
Requires-Dist: click
Requires-Dist: flask
Requires-Dist: flask_json
Requires-Dist: flask_login
Requires-Dist: tg_model>=3.11.0
Requires-Dist: tgclients
Requires-Dist: tgadmin
Requires-Dist: nextcloud-api-wrapper
Dynamic: author
Dynamic: author-email
Dynamic: license-file
Dynamic: requires-dist
Dynamic: summary
